PyVDLib/PyVDLib.py
PyVDLib/__init__.py
pyvdlib-1.1.0.dist-info/METADATA
pyvdlib-1.1.0.dist-info/WHEEL
pyvdlib-1.1.0.dist-info/licenses/LICENSE
pyvdlib-1.1.0.dist-info/RECORD
