Metadata-Version: 2.3
Name: PyVDLib
Version: 1.1.0
Summary: A library to make it easy to use the body tracking information from Virtual Desktop in Python
Project-URL: Homepage, https://www.vrdesktop.net/
Project-URL: Repo, https://github.com/DenTechs/PyVDLib
Project-URL: Issues, https://github.com/DenTechs/PyVDLib/issues
Project-URL: Discord, https://discord.gg/7eDbfgdE
Author-email: DenTechs <trdentechs+python@gmail.com>
License-File: LICENSE
Classifier: License :: OSI Approved :: MIT License
Classifier: Operating System :: Microsoft :: Windows
Classifier: Programming Language :: Python :: 3
Requires-Python: >=3.8
Requires-Dist: numpy
Requires-Dist: pywin32
